rl_test_task_3/__init__.py
rl_test_task_3/client.py
rl_test_task_3/data_exporters/__init__.py
rl_test_task_3/data_exporters/data_exporter.py
rl_test_task_3/data_exporters/generic_data_exporter.py
rl_test_task_3/data_exporters/words_data_exporter.py
rl_test_task_3/data_exporters/exceptions/__init__.py
rl_test_task_3/data_exporters/exceptions/unsupported_data_type.py
rl_test_task_3/data_providers/__init__.py
rl_test_task_3/data_providers/data_provider.py
rl_test_task_3/data_providers/input_data_provider.py
rl_test_task_3/data_providers/words_data_provider.py
rl_test_task_3/data_providers/data_parsers/__init__.py
rl_test_task_3/data_providers/data_parsers/input_data_parser.py
rl_test_task_3/data_providers/data_parsers/output_data_parser.py
rl_test_task_3/data_providers/models/__init__.py
rl_test_task_3/data_providers/models/input.py
rl_test_task_3-0.1.7.dist-info/METADATA
rl_test_task_3-0.1.7.dist-info/WHEEL
rl_test_task_3-0.1.7.dist-info/top_level.txt
rl_test_task_3-0.1.7.dist-info/RECORD
